infuse_iot/__init__.py
infuse_iot/__main__.py
infuse_iot/commands.py
infuse_iot/common.py
infuse_iot/cpatch.py
infuse_iot/credentials.py
infuse_iot/database.py
infuse_iot/rpc.py
infuse_iot/rpc_client.py
infuse_iot/serial_comms.py
infuse_iot/socket_comms.py
infuse_iot/tdf.py
infuse_iot/time.py
infuse_iot/version.py
infuse_iot/api_client/__init__.py
infuse_iot/api_client/client.py
infuse_iot/api_client/errors.py
infuse_iot/api_client/types.py
infuse_iot/api_client/api/__init__.py
infuse_iot/api_client/api/admin/__init__.py
infuse_iot/api_client/api/admin/generate_api_key.py
infuse_iot/api_client/api/board/__init__.py
infuse_iot/api_client/api/board/create_board.py
infuse_iot/api_client/api/board/get_board_by_id.py
infuse_iot/api_client/api/board/get_boards.py
infuse_iot/api_client/api/board/get_devices_by_board_id.py
infuse_iot/api_client/api/coap/__init__.py
infuse_iot/api_client/api/coap/get_coap_file_stats.py
infuse_iot/api_client/api/coap/get_coap_files.py
infuse_iot/api_client/api/default/__init__.py
infuse_iot/api_client/api/default/get_health.py
infuse_iot/api_client/api/defs/__init__.py
infuse_iot/api_client/api/defs/add_kv_definitions.py
infuse_iot/api_client/api/defs/add_rpc_definitions.py
infuse_iot/api_client/api/defs/add_tdf_definitions.py
infuse_iot/api_client/api/defs/get_kv_definitions_by_version.py
infuse_iot/api_client/api/defs/get_latest_kv_definitions.py
infuse_iot/api_client/api/defs/get_latest_rpc_definitions.py
infuse_iot/api_client/api/defs/get_latest_tdf_definitions.py
infuse_iot/api_client/api/defs/get_rpc_definitions_by_version.py
infuse_iot/api_client/api/defs/get_tdf_definitions_by_version.py
infuse_iot/api_client/api/device/__init__.py
infuse_iot/api_client/api/device/cancel_pending_device_kv_entry_updates_by_device_id_and_key_id.py
infuse_iot/api_client/api/device/create_device.py
infuse_iot/api_client/api/device/create_device_kv_entry_update_by_device_id_and_key_id.py
infuse_iot/api_client/api/device/get_device_by_device_id.py
infuse_iot-0.6.0.dist-info/licenses/LICENSE.md
infuse_iot-0.6.0.dist-info/METADATA
infuse_iot-0.6.0.dist-info/WHEEL
infuse_iot-0.6.0.dist-info/entry_points.txt
infuse_iot-0.6.0.dist-info/top_level.txt
infuse_iot-0.6.0.dist-info/RECORD
