Metadata-Version: 2.4
Name: infuse_iot
Version: 0.6.0
Summary: Infuse-IoT Platform python package
Author-email: Embeint Holdings Pty Ltd <support@embeint.com>
License-Expression: LicenseRef-FSL-1.1-ALv2
Project-URL: Homepage, https://github.com/Embeint/python-tools
Project-URL: Issues, https://github.com/Embeint/python-tools/issues
Classifier: Programming Language :: Python :: 3
Classifier: Operating System :: POSIX :: Linux
Classifier: Operating System :: MacOS :: MacOS X
Classifier: Operating System :: Microsoft :: Windows
Requires-Python: >=3.10
License-File: LICENSE.md
Requires-Dist: argcomplete
Requires-Dist: aiohttp
Requires-Dist: attrs
Requires-Dist: bleak
Requires-Dist: cryptography
Requires-Dist: colorama
Requires-Dist: httpx
Requires-Dist: pylink-square
Requires-Dist: pyserial
Requires-Dist: python-dateutil
Requires-Dist: rich
Requires-Dist: simple-term-menu
Requires-Dist: tabulate
Requires-Dist: keyring
Requires-Dist: pyocd
Requires-Dist: pyyaml
Requires-Dist: paho-mqtt
Dynamic: license-file
